docstamp/__init__.py
docstamp/collections.py
docstamp/commands.py
docstamp/config.py
docstamp/data_source.py
docstamp/file_utils.py
docstamp/gdrive.py
docstamp/inkscape.py
docstamp/model.py
docstamp/pdf_utils.py
docstamp/pdflatex.py
docstamp/qrcode.py
docstamp/svg_fonts.py
docstamp/svg_utils.py
docstamp/template.py
docstamp/unicode_csv.py
docstamp/vcard.py
docstamp/version.py
docstamp/xml_utils.py
docstamp/cli/__init__.py
docstamp/cli/cli.py
docstamp/cli/utils.py
docstamp-0.3.5.data/scripts/embed_font_to_svg.py
docstamp-0.3.5.data/scripts/svg_export.py
docstamp-0.3.5.dist-info/METADATA
docstamp-0.3.5.dist-info/RECORD
docstamp-0.3.5.dist-info/WHEEL
docstamp-0.3.5.dist-info/entry_points.txt
docstamp-0.3.5.dist-info/top_level.txt
