Metadata-Version: 2.1
Name: docstamp
Version: 0.3.5
Summary: A SVG and LateX template renderer from table data based on Inkscape and Jinja2.
Home-page: https://github.com/PythonSanSebastian/docstamp.git
Author: Alexandre M. Savio
Author-email: alexsavio@gmail.com
Maintainer: Alexandre M. Savio
Maintainer-email: alexsavio@gmail.com
License: new BSD
Platform: Linux/MacOSX
Classifier: Development Status :: 4 - Beta
Classifier: Programming Language :: Python
Classifier: Programming Language :: Python :: 3
Classifier: Programming Language :: Python :: 3.4
Classifier: Programming Language :: Python :: 3.5
Classifier: Programming Language :: Python :: 3.6
Requires-Dist: Pillow (>=3.1.0)
Requires-Dist: jinja2 (>=2.8)
Requires-Dist: gspread (>=0.3.0)
Requires-Dist: oauth2client (>=2.0.0)
Requires-Dist: PyPDF2 (>=1.25.1)
Requires-Dist: qrcode (>=5.1)
Requires-Dist: svgutils (==0.2.0)
Requires-Dist: click (>=6.6)
